Metadata-Version: 2.4
Name: hydro_analysis_toolkit
Version: 0.8.2
Summary: ECMWF's Hydrological Analysis Toolkit
Author-email: "European Centre for Medium-Range Weather Forecasts (ECMWF)" <software.support@ecmwf.int>
Maintainer-email: Corentin Carton de Wiart <corentin.carton@ecmwf.int>, "Oisín M. Morrison" <oisin.morrison@ecmwf.int>
License: Apache License Version 2.0
Project-URL: repository, https://github.com/ecmwf/hat
Project-URL: documentation, https://hydro-analysis-toolkit.readthedocs.io
Project-URL: issues, https://github.com/ecmwf/hat/issues
Classifier: Development Status :: 4 - Beta
Classifier: Intended Audience :: Science/Research
Classifier: Natural Language :: English
Classifier: License :: OSI Approved :: Apache Software License
Classifier: Operating System :: OS Independent
Classifier: Programming Language :: Python :: 3 :: Only
Classifier: Programming Language :: Python :: 3.9
Classifier: Programming Language :: Python :: 3.10
Classifier: Programming Language :: Python :: 3.11
Classifier: Programming Language :: Python :: 3.12
Classifier: Programming Language :: Python :: 3.13
Classifier: Topic :: Scientific/Engineering
Requires-Python: >=3.9
License-File: LICENSE
Requires-Dist: numpy
Requires-Dist: pandas
Requires-Dist: xarray
Requires-Dist: matplotlib
Requires-Dist: geopandas
Requires-Dist: typer
Requires-Dist: humanize
Requires-Dist: tqdm
Requires-Dist: ipyleaflet
Requires-Dist: ipywidgets
Requires-Dist: earthkit-data>=0.13.8
Requires-Dist: earthkit-hydro
Requires-Dist: earthkit-meteo
Requires-Dist: cfgrib
Requires-Dist: netCDF4
Requires-Dist: eccodes
Requires-Dist: plotly
Requires-Dist: floods-html
Requires-Dist: geopy
Requires-Dist: setuptools
Requires-Dist: anywidget
Provides-Extra: test
Requires-Dist: pytest; extra == "test"
Provides-Extra: dev
Requires-Dist: pytest; extra == "dev"
Requires-Dist: ruff; extra == "dev"
Requires-Dist: pre-commit; extra == "dev"
Dynamic: license-file
